mptcpanalyzer/__init__.py
mptcpanalyzer/cache.py
mptcpanalyzer/cli.py
mptcpanalyzer/command.py
mptcpanalyzer/command_example.py
mptcpanalyzer/config.py
mptcpanalyzer/connection.py
mptcpanalyzer/core.py
mptcpanalyzer/data.py
mptcpanalyzer/debug.py
mptcpanalyzer/exporter.py
mptcpanalyzer/metadata.py
mptcpanalyzer/overhead.py
mptcpanalyzer/parser.py
mptcpanalyzer/pdutils.py
mptcpanalyzer/plot.py
mptcpanalyzer/sqlite_helpers.py
mptcpanalyzer/statistics.py
mptcpanalyzer/tshark.py
mptcpanalyzer/version.py
mptcpanalyzer/plots/__init__.py
mptcpanalyzer/plots/aggr_benefit.py
mptcpanalyzer/plots/dss.py
mptcpanalyzer/plots/goodput.py
mptcpanalyzer/plots/interarrival.py
mptcpanalyzer/plots/ns3.py
mptcpanalyzer/plots/owd.py
mptcpanalyzer/plots/reinjections.py
mptcpanalyzer/plots/stream.py
mptcpanalyzer/plots/throughput.py
tests/__init__.py
tests/analysis_test.py
tests/cache_test.py
tests/config_test.py
tests/integration_test.py
tests/mptcpanalyzer_test.py
tests/owd_test.py
tests/plugins_test.py
mptcpanalyzer-0.3.2.dist-info/METADATA
mptcpanalyzer-0.3.2.dist-info/WHEEL
mptcpanalyzer-0.3.2.dist-info/dependency_links.txt
mptcpanalyzer-0.3.2.dist-info/entry_points.txt
mptcpanalyzer-0.3.2.dist-info/top_level.txt
mptcpanalyzer-0.3.2.dist-info/RECORD
