Metadata-Version: 2.1
Name: mptcpanalyzer
Version: 0.3.2
Summary: Analyze mptcp traces (.pcap)
Home-page: http://github.com/teto/mptcpanalyzer
Author: Matthieu Coudron
Author-email: coudron@iij.ad.jp
License: GPL
Keywords: mptcp analysis pcap
Platform: UNKNOWN
Classifier: Development Status :: 4 - Beta
Classifier: License :: OSI Approved :: GNU General Public License v3 (GPLv3)
Classifier: Intended Audience :: System Administrators
Classifier: Intended Audience :: Science/Research
Classifier: Intended Audience :: Telecommunications Industry
Classifier: Environment :: Console
Classifier: Programming Language :: Python :: 3.7
Requires-Dist: stevedore
Requires-Dist: matplotlib (>=3.0.3)
Requires-Dist: pandas (>=0.25)
Requires-Dist: cmd2 (>=0.9.15)
